bridgeapi/__about__.py
bridgeapi/__init__.py
bridgeapi/base_client.py
bridgeapi/client.py
bridgeapi/exceptions.py
bridgeapi/models.py
bridgeapi-1.1.0.dist-info/METADATA
bridgeapi-1.1.0.dist-info/WHEEL
bridgeapi-1.1.0.dist-info/licenses/LICENSE.txt
bridgeapi-1.1.0.dist-info/RECORD
