Metadata-Version: 2.1
Name: bridgeapi
Version: 1.1.0
Summary: Client for the Bridge open banking API aggregator
Project-URL: Documentation, https://gitlab.com/alex-marty/bridgeapi
Project-URL: Issues, https://gitlab.com/alex-marty/bridgeapi/-/issues
Project-URL: Source, https://gitlab.com/alex-marty/bridgeapi
Author-email: Alexandre Marty <contact@marty.in>
License-Expression: MIT
License-File: LICENSE.txt
Classifier: Development Status :: 4 - Beta
Classifier: Programming Language :: Python
Classifier: Programming Language :: Python :: 3.10
Classifier: Programming Language :: Python :: 3.11
Classifier: Programming Language :: Python :: Implementation :: CPython
Classifier: Programming Language :: Python :: Implementation :: PyPy
Requires-Python: >=3.10
Requires-Dist: pydantic>=2
Requires-Dist: requests
